sparseba/__init__.py
sparseba/core.py
sparseba/indices.py
sparseba/utils.py
sparseba-0.0.1.dist-info/LICENSE
sparseba-0.0.1.dist-info/METADATA
sparseba-0.0.1.dist-info/WHEEL
sparseba-0.0.1.dist-info/top_level.txt
sparseba-0.0.1.dist-info/RECORD
